tiny_model/__init__.py
tiny_model/lm.py
tiny_model/lm_modules.py
tiny_model/sparse_mlp.py
tiny_model/tokenization/neo_tok_ids_to_ts.pt
tiny_model/tokenization/tokenization.py
tiny_model/tokenization/ts_tok_ids_to_neo.pt
tinymodel-0.1.2.post3.dist-info/METADATA
tinymodel-0.1.2.post3.dist-info/WHEEL
tinymodel-0.1.2.post3.dist-info/RECORD
