Metadata-Version: 2.1
Name: tinymodel
Version: 0.1.2.post3
Summary: A small TinyStories LM with SAEs and transcoders
Author: Noa Nabeshima
Author-email: noanabeshima@gmail.com
Requires-Python: >=3.11,<4.0
Classifier: Programming Language :: Python :: 3
Classifier: Programming Language :: Python :: 3.11
Classifier: Programming Language :: Python :: 3.12
Requires-Dist: datasets (>=2.20.0,<3.0.0)
Requires-Dist: einops (>=0.8.0,<0.9.0)
Requires-Dist: huggingface-hub (>=0.23.4,<0.24.0)
Requires-Dist: numpy (>=1.26.4,<2.0.0)
Requires-Dist: torch (>=2.3.1,<3.0.0)
Requires-Dist: tqdm (>=4.66.4,<5.0.0)
Requires-Dist: transformers (>=4.41.2,<5.0.0)
Requires-Dist: unidecode (>=1.3.8,<2.0.0)
